Metadata-Version: 2.1
Name: odoo-addon-account_avatax_exemption
Version: 18.0.1.0.0.5
Requires-Python: >=3.10
Requires-Dist: Avalara
Requires-Dist: odoo-addon-account_avatax_exemption_base==18.0.*
Requires-Dist: odoo-addon-account_avatax_oca==18.0.*
Requires-Dist: odoo-addon-account_avatax_sale_oca==18.0.*
Requires-Dist: odoo-addon-queue_job==18.0.*
Requires-Dist: odoo==18.0.*
Summary: This application allows you to add exemptions to Avatax
Home-page: https://github.com/OCA/account-fiscal-rule
License: AGPL-3
Author: Sodexis, Odoo Community Association (OCA)
Author-email: support@odoo-community.org
Classifier: Programming Language :: Python
Classifier: Framework :: Odoo
Classifier: Framework :: Odoo :: 18.0
Classifier: License :: OSI Approved :: GNU Affero General Public License v3
